ci_tools/__init__.py
ci_tools/attach_pipeline_policy.py
ci_tools/gh_secrets_and_vars_async.py
leadmo_api/__init__.py
leadmo_api/models/__init__.py
leadmo_api/models/appointment_endpoint_params.py
leadmo_api/models/common.py
leadmo_api/models/contact_endpoint_params.py
leadmo_api/models/workflow_endpoint_params.py
leadmo_api/util.py
leadmo_api/v1/__init__.py
leadmo_api/v1/appointments_endpoints.py
leadmo_api/v1/client.py
leadmo_api/v1/contact_endpoints.py
leadmo_api/v1/workflow_endpoints.py
augint_tools-1.42.0.dist-info/METADATA
augint_tools-1.42.0.dist-info/WHEEL
augint_tools-1.42.0.dist-info/entry_points.txt
augint_tools-1.42.0.dist-info/RECORD
