Metadata-Version: 2.1
Name: augint-tools
Version: 1.42.0
Summary: Standard tools for Augmenting Integrations
Home-page: https://github.com/svange/openbrain
License: AGPL-3.0-only
Author: Samuel Vange
Author-email: 7166607+svange@users.noreply.github.com
Requires-Python: >=3.10,<4.0
Classifier: License :: OSI Approved :: GNU Affero General Public License v3
Classifier: Programming Language :: Python :: 3
Classifier: Programming Language :: Python :: 3.10
Classifier: Programming Language :: Python :: 3.11
Classifier: Programming Language :: Python :: 3.12
Provides-Extra: docs
Requires-Dist: aws-lambda-powertools (>=2.42.0,<3.0.0)
Requires-Dist: boto3 (>=1.28.51,<2.0.0)
Requires-Dist: loguru (>=0.7.2,<0.8.0)
Requires-Dist: pydantic[email] (>=2.8.2,<3.0.0)
Requires-Dist: pygithub (>=2.3.0,<3.0.0)
Requires-Dist: python-dotenv (>=1.0.1,<2.0.0)
Requires-Dist: pytz (>=2024.1,<2025.0)
Requires-Dist: rich (>=13.7.1,<14.0.0)
Requires-Dist: sphinx (>=7.4.7,<9.0.0) ; extra == "docs"
Requires-Dist: sphinx-click (>=6.0.0,<7.0.0) ; extra == "docs"
